<?xml version="1.0" encoding="UTF-8"?>
<object name="weblcms_learning_path_question_attempts">
 <properties>
  <property name="id" type="integer" unsigned="1" notnull="1" />
  <property name="assessment_attempt_id" type="integer" unsigned="1" notnull="1" />
  <property name="question_id" type="integer" unsigned="1" notnull="1" />
  <property name="answer" type="text"/>
  <property name="answer_idx" type="integer" unsigned="1" default="0"/>
  <property name="feedback" type="integer" unsigned="1" default="0"/>
  <property name="score" type="integer" />
  <property name="date" type="timestamp" notnull="1" />
 </properties>
 <index name="id" type="primary">
  <indexproperty name="id"/>
 </index>
 <index name="learning_path_assessment_attempt_id">
  <indexproperty name="learning_path_assessment_attempt_id"/>
 </index>
</object>